CHANGES.rst
CONTRIBUTORS.txt
LICENSE.txt
MANIFEST.in
README.rst
setup.py
test/port_helpers.py
yieldfrom/__init__.py
yieldfrom.urllib3.egg-info/PKG-INFO
yieldfrom.urllib3.egg-info/SOURCES.txt
yieldfrom.urllib3.egg-info/dependency_links.txt
yieldfrom.urllib3.egg-info/namespace_packages.txt
yieldfrom.urllib3.egg-info/not-zip-safe
yieldfrom.urllib3.egg-info/requires.txt
yieldfrom.urllib3.egg-info/top_level.txt
yieldfrom/urllib3/__init__.py
yieldfrom/urllib3/_collections.py
yieldfrom/urllib3/connection.py
yieldfrom/urllib3/connectionpool.py
yieldfrom/urllib3/exceptions.py
yieldfrom/urllib3/fields.py
yieldfrom/urllib3/filepost.py
yieldfrom/urllib3/poolmanager.py
yieldfrom/urllib3/request.py
yieldfrom/urllib3/response.py
yieldfrom/urllib3/packages/__init__.py
yieldfrom/urllib3/packages/ordered_dict.py
yieldfrom/urllib3/packages/six.py
yieldfrom/urllib3/packages/ssl_match_hostname/__init__.py
yieldfrom/urllib3/packages/ssl_match_hostname/_implementation.py
yieldfrom/urllib3/util/__init__.py
yieldfrom/urllib3/util/connection.py
yieldfrom/urllib3/util/request.py
yieldfrom/urllib3/util/response.py
yieldfrom/urllib3/util/retry.py
yieldfrom/urllib3/util/ssl_.py
yieldfrom/urllib3/util/timeout.py
yieldfrom/urllib3/util/url.py