Metadata-Version: 1.1
Name: yieldfrom.urllib3
Version: 0.1.4
Summary: Asyncio HTTP library with thread-safe connection pooling, file post, and more.
Home-page: http://urllib3.readthedocs.org/
Author: David Keeney
Author-email: dkeeney@rdbhost.com
License: MIT
Keywords: urllib httplib asyncio filepost http https ssl pooling
Platform: UNKNOWN
Classifier: Environment :: Web Environment
Classifier: Intended Audience :: Developers
Classifier: License :: OSI Approved :: MIT License
Classifier: Operating System :: OS Independent
Classifier: Programming Language :: Python
Classifier: Programming Language :: Python :: 3
Classifier: Topic :: Internet :: WWW/HTTP
Classifier: Topic :: Software Development :: Libraries
